axi_dma_stream_microblaze/vivado/ip/uart/rtl/crc_ccitt.v
// vim: ts=4 sw=4 noexpandtab

// THIS IS GENERATED CODE.
// 
// This code is Public Domain.
// Permission to use, copy, modify, and/or distribute this software for any
// purpose with or without fee is hereby granted.
// 
// THE SOFTWARE IS PROVIDED "AS IS" AND THE AUTHOR DISCLAIMS ALL WARRANTIES
// WITH REGARD TO THIS SOFTWARE INCLUDING ALL IMPLIED WARRANTIES OF
// MERCHANTABILITY AND FITNESS. IN NO EVENT SHALL THE AUTHOR BE LIABLE FOR ANY
// SPECIAL, DIRECT, INDIRECT, OR CONSEQUENTIAL DAMAGES OR ANY DAMAGES WHATSOEVER
// RESULTING FROM LOSS OF USE, DATA OR PROFITS, WHETHER IN AN ACTION OF CONTRACT,
// NEGLIGENCE OR OTHER TORTIOUS ACTION, ARISING OUT OF OR IN CONNECTION WITH THE
// USE OR PERFORMANCE OF THIS SOFTWARE.

`ifndef CRC_V_
`define CRC_V_

// CRC polynomial coefficients: x^16 + x^12 + x^5 + 1
//                              0x1021 (hex)
// CRC width:                   16 bits
// CRC shift direction:         left

module crc_ccitt (
	input wire [15:0] crcIn,
	input wire [7:0] data,
	output wire [15:0] crcOut
);
	assign crcOut[0] = (crcIn[8] ^ crcIn[12] ^ data[0] ^ data[4]);
	assign crcOut[1] = (crcIn[9] ^ crcIn[13] ^ data[1] ^ data[5]);
	assign crcOut[2] = (crcIn[10] ^ crcIn[14] ^ data[2] ^ data[6]);
	assign crcOut[3] = (crcIn[11] ^ crcIn[15] ^ data[3] ^ data[7]);
	assign crcOut[4] = (crcIn[12] ^ data[4]);
	assign crcOut[5] = (crcIn[8] ^ crcIn[12] ^ crcIn[13] ^ data[0] ^ data[4] ^ data[5]);
	assign crcOut[6] = (crcIn[9] ^ crcIn[13] ^ crcIn[14] ^ data[1] ^ data[5] ^ data[6]);
	assign crcOut[7] = (crcIn[10] ^ crcIn[14] ^ crcIn[15] ^ data[2] ^ data[6] ^ data[7]);
	assign crcOut[8] = (crcIn[0] ^ crcIn[11] ^ crcIn[15] ^ data[3] ^ data[7]);
	assign crcOut[9] = (crcIn[1] ^ crcIn[12] ^ data[4]);
	assign crcOut[10] = (crcIn[2] ^ crcIn[13] ^ data[5]);
	assign crcOut[11] = (crcIn[3] ^ crcIn[14] ^ data[6]);
	assign crcOut[12] = (crcIn[4] ^ crcIn[8] ^ crcIn[12] ^ crcIn[15] ^ data[0] ^ data[4] ^ data[7]);
	assign crcOut[13] = (crcIn[5] ^ crcIn[9] ^ crcIn[13] ^ data[1] ^ data[5]);
	assign crcOut[14] = (crcIn[6] ^ crcIn[10] ^ crcIn[14] ^ data[2] ^ data[6]);
	assign crcOut[15] = (crcIn[7] ^ crcIn[11] ^ crcIn[15] ^ data[3] ^ data[7]);
endmodule

`endif // CRC_V_

axi_dma_stream_microblaze/vivado/ip/uart/rtl/axis_tx_protocol_crc.v
`default_nettype none

/* CRC was generated by https://bues.ch/cms/hacking/crcgen */

module axis_tx_protocol_crc 
		(
    input  wire       axis_aclk,
    input  wire       axis_reset,

    /* AXI input */
    input  wire [7:0]  s_axis_tdata,
    input  wire        s_axis_tvalid,
    output wire        s_axis_tready,
	input wire         s_axis_tlast,

    /* AXI output */
    output wire [7:0]  m_axis_tdata,
    output wire        m_axis_tvalid,
    input  wire        m_axis_tready,
    output wire        m_axis_tlast);


localparam  start_state = 2'h0,
            ready_state = 2'h1,
            tlast_state = 2'h2,
            done_state =  2'h3;

reg [15:0] curr_crc;
wire [15:0] crc_out;
reg [1:0] state;
reg [7:0] crc_data;

assign m_axis_tdata =  (state < tlast_state)?s_axis_tdata:crc_data;
assign m_axis_tvalid = (state < tlast_state)?s_axis_tvalid:m_axis_tready;
assign m_axis_tlast =  (state==done_state)?1'b1:1'b0;
assign s_axis_tready = m_axis_tready & (state == ready_state);

crc_ccitt  crc_engine(.crcIn(curr_crc),.data(s_axis_tdata),.crcOut(crc_out));

initial begin
    state = start_state;
end                

always @(posedge axis_aclk) begin

    if (!axis_reset) begin
        state <= start_state;
    end
    else begin 
        case(state)
            start_state: begin
                curr_crc <= 16'hFFFF;
                state <= ready_state;
            end

        ready_state: begin
            if (s_axis_tvalid & m_axis_tready ) begin
                curr_crc <= crc_out;
                if (s_axis_tlast) begin
                    crc_data <= crc_out[15:8];
                    state <= tlast_state;
                    $display("changing states");
                end
            end
        end
        tlast_state: begin
            if ( m_axis_tready) begin
                $display("high CRC");
                crc_data <= curr_crc[7:0];
                state <= done_state; 
            end

        end
        done_state: begin
            if ( m_axis_tready) begin
                state <= start_state; 
                 $display("LOW CRC");
            end
        end

        endcase
  end
end
endmodule
/* eof */

axi_dma_stream_microblaze/vivado/ip/uart/tb/axis_protocol_crc_tb.v
//////////////////////////////////////////////////////////////////////
// File Downloaded from http://www.nandland.com
//////////////////////////////////////////////////////////////////////

// This testbench will exercise the UART RX.
// It sends out byte 0x37, and ensures the RX receives it correctly.
`timescale 1ns/10ps

`include "../rtl/axis_tx_protocol_crc.v"

module axis_protocol_crc_tb();


reg clk = 0;
wire tx ;

//AXI input (TX)
reg  [7:0]  s_axis_tdata= 0;
reg         s_axis_tvalid = 0;
reg         s_axis_tlast = 0;
wire        s_axis_tready;


//AXI output (RX)
wire [7:0]ma_axis_tdata;
wire ma_axis_tvalid;
reg ma_axis_tready = 1;
wire ma_axis_tlast;

reg reset_l =0;

axis_tx_protocol_crc 
  UUT(.axis_aclk(clk),
    .axis_reset(reset_l),
     .s_axis_tdata(s_axis_tdata),
     .s_axis_tvalid(s_axis_tvalid),
     .s_axis_tready(s_axis_tready),
     .s_axis_tlast(s_axis_tlast),
     .m_axis_tdata(ma_axis_tdata),
     .m_axis_tvalid(ma_axis_tvalid),
     .m_axis_tready(ma_axis_tready),
     .m_axis_tlast(ma_axis_tlast));

  
  // Clock Generators:
  always
    #1 clk <= !clk;


initial begin
     $dumpfile("axis_tx_protocol_tb.vcd");
     $dumpvars;

  // Main Testing:
  /*
0 1 2 3 4 5 6 7 8 9 
CRC=0xC241
  */
  	
	@(posedge clk); reset_l <= 0;
	@(posedge clk); reset_l <= 1;

    #10;

    //0
    @(posedge clk); if (s_axis_tready ) 
                    begin
                      s_axis_tvalid <= 1'b1;
                      s_axis_tdata <= 8'h0;
                    end
                
    //1
    @(posedge clk); if (s_axis_tready ) 
                    begin
                      s_axis_tdata <= 8'h1;
                    end    

    //2
    @(posedge clk); if (s_axis_tready ) 
                    begin
                      s_axis_tdata <= 8'h2;
                    end                        
    //3
    @(posedge clk); if (s_axis_tready ) 
                    begin
                      s_axis_tdata <= 8'h3;
                    end    

    //4
    @(posedge clk); if (s_axis_tready ) 
                    begin
                      s_axis_tdata <= 8'h4;
                    end    

    //5
    @(posedge clk); if (s_axis_tready ) 
                    begin
                      s_axis_tdata <= 8'h5;
                    end    

    //6
    @(posedge clk); if (s_axis_tready ) 
                    begin
                      s_axis_tdata <= 8'h6;
                    end                                            

    //7
    @(posedge clk); if (s_axis_tready ) 
                    begin
                      s_axis_tdata <= 8'h7;
                    end    

    //8
    @(posedge clk); if (s_axis_tready ) 
                    begin
                      s_axis_tdata <= 8'h8;
                    end    

    //9
    @(posedge clk); if (s_axis_tready ) 
                    begin
                      s_axis_tdata <= 8'h9;
                      s_axis_tlast <= 1;
                    end    

    @(posedge clk); s_axis_tvalid <= 0;     
                    s_axis_tlast <= 0;
                                    
    #100000;
    $finish();

end    

endmodule

axi_dma_stream_microblaze/vivado/axis_dma/axis_dma.sim/sim_1/behav/xsim/axis_tx_protocol_tb.vcd
$date
   Thu Aug 27 21:27:11 2020
$end
$version
  2020.1
$end
$timescale
  1ps
$end
$scope module axis_protocol_crc_tb $end
$var reg 1 ! clk $end
$var wire 1 " tx $end
$var reg 8 # s_axis_tdata [7:0] $end
$var reg 1 $ s_axis_tvalid $end
$var reg 1 % s_axis_tlast $end
$var wire 1 & s_axis_tready $end
$var wire 8 ' ma_axis_tdata [7:0] $end
$var wire 1 ( ma_axis_tvalid $end
$var reg 1 ) ma_axis_tready $end
$var wire 1 * ma_axis_tlast $end
$var reg 1 + reset_l $end
$scope module UUT $end
$var wire 1 , axis_aclk $end
$var wire 1 - axis_reset $end
$var wire 8 . s_axis_tdata [7:0] $end
$var wire 1 / s_axis_tvalid $end
$var wire 1 & s_axis_tready $end
$var wire 1 0 s_axis_tlast $end
$var wire 8 ' m_axis_tdata [7:0] $end
$var wire 1 ( m_axis_tvalid $end
$var wire 1 1 m_axis_tready $end
$var wire 1 * m_axis_tlast $end
$var reg 16 2 curr_crc [15:0] $end
$var wire 16 3 crc_out [15:0] $end
$var reg 2 4 state [1:0] $end
$var reg 8 5 crc_data [7:0] $end
$var parameter 2 6 start_state [1:0] $end
$var parameter 2 7 ready_state [1:0] $end
$var parameter 2 8 tlast_state [1:0] $end
$var parameter 2 9 done_state [1:0] $end
$scope module crc_engine $end
$var wire 16 : crcIn [15:0] $end
$var wire 8 . data [7:0] $end
$var wire 16 3 crcOut [15:0] $end
$upscope $end
$upscope $end
$upscope $end
$enddefinitions $end
#0
$dumpvars
0!
z"
b0 #
0$
0%
0&
b0 '
0(
1)
0*
0+
0,
0-
b0 .
0/
00
11
bx 2
bx 3
b0 4
bx 5
b0 6
b1 7
b10 8
b11 9
bx :
$end
#1000
1!
0+
1,
b0 4
#2000
0!
0,
#3000
1!
1+
1,
1-
b0 4
#4000
0!
0,
#5000
1!
1&
b0 '
0(
0*
1,
b1111111111111111 2
b1110000111110000 3
b1 4
b1111111111111111 :
#6000
0!
0,
#7000
1!
1,
#8000
0!
0,
#9000
1!
1,
#10000
0!
0,
#11000
1!
1,
#12000
0!
0,
#13000
1!
b0 #
1$
1(
1,
1/
#14000
0!
0,
#15000
1!
b1 #
b1 '
1,
b1 .
b1110000111110000 2
b110100101110 3
b1110000111110000 :
#16000
0!
0,
#17000
1!
b10 #
b10 '
1,
b10 .
b110100101110 2
b1101111111101111 3
b110100101110 :
#18000
0!
0,
#19000
1!
b11 #
b11 '
1,
b11 .
b1101111111101111 2
b1110010111110001 3
b1101111111101111 :
#20000
0!
0,
#21000
1!
b100 #
b100 '
1,
b100 .
b1110010111110001 2
b1110000001111 3
b1110010111110001 :
#22000
0!
0,
#23000
1!
b101 #
b101 '
1,
b101 .
b1110000001111 2
b1000110000011000 3
b1110000001111 :
#24000
0!
0,
#25000
1!
b110 #
b110 '
1,
b110 .
b1000110000011000 2
b10100011000010 3
b1000110000011000 :
#26000
0!
0,
#27000
1!
b111 #
b111 '
1,
b111 .
b10100011000010 2
b1011110001101 3
b10100011000010 :
#28000
0!
0,
#29000
1!
b1000 #
b1000 '
1,
b1000 .
b1011110001101 2
b110111011011110 3
b1011110001101 :
#30000
0!
0,
#31000
1!
b1001 #
1%
b1001 '
1,
b1001 .
10
b110111011011110 2
b1100001001000001 3
b110111011011110 :
#32000
0!
0,
#33000
1!
0$
0%
0&
b11000010 '
1(
0*
1,
0/
00
b1100001001000001 2
b10100100100111 3
b10 4
b11000010 5
b1100001001000001 :
#34000
0!
0,
#35000
1!
0&
b1000001 '
1(
1*
1,
b11 4
b1000001 5
#36000
0!
0,
#37000
1!
0&
b1001 '
0(
0*
1,
b0 4
#38000
0!
0,
#39000
1!
1&
b1001 '
0(
0*
1,
b1111111111111111 2
b111000011011001 3
b1 4
b1111111111111111 :
